{
  "parent": "minecraft:recipes/root",
  "criteria": {
    "has_cejl": {
      "conditions": {
        "items": [
          {
            "items": [
              "megalovania:cejl"
            ]
          }
        ]
      },
      "trigger": "minecraft:inventory_changed"
    },
    "has_the_recipe": {
      "conditions": {
        "recipe": "megalovania:cejl_block"
      },
      "trigger": "minecraft:recipe_unlocked"
    }
  },
  "requirements": [
    [
      "has_cejl",
      "has_the_recipe"
    ]
  ],
  "rewards": {
    "recipes": [
      "megalovania:cejl_block"
    ]
  }
}